{
"meta":{"test_sets":[],"test_metrics":[],"learn_metrics":[{"best_value":"Min","name":"MultiClass"}],"launch_mode":"Train","parameters":"","iteration_count":300,"learn_sets":["learn"],"name":"experiment"},
"iterations":[
{"learn":[1.373538308],"iteration":0,"passed_time":0.2083580609,"remaining_time":62.29906021},
{"learn":[1.367110166],"iteration":1,"passed_time":0.2609617762,"remaining_time":38.88330465},
{"learn":[1.345967269],"iteration":2,"passed_time":0.3105957978,"remaining_time":30.74898398},
{"learn":[1.33464698],"iteration":3,"passed_time":0.3670815341,"remaining_time":27.16403352},
{"learn":[1.322507939],"iteration":4,"passed_time":0.4210238964,"remaining_time":24.84040988},
{"learn":[1.310436166],"iteration":5,"passed_time":0.4708655783,"remaining_time":23.07241334},
{"learn":[1.30138474],"iteration":6,"passed_time":0.5349597505,"remaining_time":22.3918867},
{"learn":[1.293185944],"iteration":7,"passed_time":0.5916620295,"remaining_time":21.59566408},
{"learn":[1.286551033],"iteration":8,"passed_time":0.6472427359,"remaining_time":20.92751513},
{"learn":[1.281175501],"iteration":9,"passed_time":0.7024033667,"remaining_time":20.36969763},
{"learn":[1.272412614],"iteration":10,"passed_time":0.7614573327,"remaining_time":20.00556083},
{"learn":[1.260983415],"iteration":11,"passed_time":0.8189436217,"remaining_time":19.65464692},
{"learn":[1.254201856],"iteration":12,"passed_time":0.872143727,"remaining_time":19.25424997},
{"learn":[1.249234918],"iteration":13,"passed_time":0.9306027024,"remaining_time":19.01088378},
{"learn":[1.240449388],"iteration":14,"passed_time":0.9863468443,"remaining_time":18.74059004},
{"learn":[1.229289509],"iteration":15,"passed_time":1.042323718,"remaining_time":18.50124599},
{"learn":[1.223241595],"iteration":16,"passed_time":1.097134543,"remaining_time":18.26406328},
{"learn":[1.212493411],"iteration":17,"passed_time":1.160041256,"remaining_time":18.17397967},
{"learn":[1.204996584],"iteration":18,"passed_time":1.213950442,"remaining_time":17.95368812},
{"learn":[1.195738074],"iteration":19,"passed_time":1.267386855,"remaining_time":17.74341597},
{"learn":[1.187524066],"iteration":20,"passed_time":1.322620454,"remaining_time":17.57195746},
{"learn":[1.177310733],"iteration":21,"passed_time":1.370500212,"remaining_time":17.31813904},
{"learn":[1.167690327],"iteration":22,"passed_time":1.424087944,"remaining_time":17.1509722},
{"learn":[1.158127499],"iteration":23,"passed_time":1.479934795,"remaining_time":17.01925014},
{"learn":[1.15156308],"iteration":24,"passed_time":1.541354071,"remaining_time":16.95489478},
{"learn":[1.146983279],"iteration":25,"passed_time":1.592519113,"remaining_time":16.78270142},
{"learn":[1.138284302],"iteration":26,"passed_time":1.648638157,"remaining_time":16.66956359},
{"learn":[1.132753988],"iteration":27,"passed_time":1.699723104,"remaining_time":16.51159587},
{"learn":[1.122071766],"iteration":28,"passed_time":1.754876372,"remaining_time":16.39901713},
{"learn":[1.112752775],"iteration":29,"passed_time":1.835754903,"remaining_time":16.52179413},
{"learn":[1.106531666],"iteration":30,"passed_time":1.887087709,"remaining_time":16.37505141},
{"learn":[1.097818745],"iteration":31,"passed_time":1.953730902,"remaining_time":16.36249631},
{"learn":[1.089657919],"iteration":32,"passed_time":2.01035094,"remaining_time":16.26556669},
{"learn":[1.08434369],"iteration":33,"passed_time":2.068486967,"remaining_time":16.18286862},
{"learn":[1.074764513],"iteration":34,"passed_time":2.131219602,"remaining_time":16.13637699},
{"learn":[1.069435858],"iteration":35,"passed_time":2.195992436,"remaining_time":16.10394453},
{"learn":[1.064579642],"iteration":36,"passed_time":2.256645276,"remaining_time":16.04047859},
{"learn":[1.062350081],"iteration":37,"passed_time":2.277447753,"remaining_time":15.70240293},
{"learn":[1.057510343],"iteration":38,"passed_time":2.337712605,"remaining_time":15.64469205},
{"learn":[1.051973011],"iteration":39,"passed_time":2.390004211,"remaining_time":15.53502737},
{"learn":[1.03789991],"iteration":40,"passed_time":2.441546176,"remaining_time":15.42342585},
{"learn":[1.03119624],"iteration":41,"passed_time":2.48901295,"remaining_time":15.28965098},
{"learn":[1.012982151],"iteration":42,"passed_time":2.545026862,"remaining_time":15.2109745},
{"learn":[1.010607751],"iteration":43,"passed_time":2.599528797,"remaining_time":15.12453118},
{"learn":[1.004825107],"iteration":44,"passed_time":2.658305685,"remaining_time":15.06373222},
{"learn":[0.9978842459],"iteration":45,"passed_time":2.717582213,"remaining_time":15.00578005},
{"learn":[0.9908413594],"iteration":46,"passed_time":2.772909484,"remaining_time":14.92651275},
{"learn":[0.9846557917],"iteration":47,"passed_time":2.836575024,"remaining_time":14.89201888},
{"learn":[0.9751583582],"iteration":48,"passed_time":2.893672884,"remaining_time":14.82269171},
{"learn":[0.9656531094],"iteration":49,"passed_time":2.949551171,"remaining_time":14.74775585},
{"learn":[0.9615741758],"iteration":50,"passed_time":3.010610736,"remaining_time":14.69886418},
{"learn":[0.9520840836],"iteration":51,"passed_time":3.065578817,"remaining_time":14.62045282},
{"learn":[0.9432499322],"iteration":52,"passed_time":3.12803961,"remaining_time":14.57784498},
{"learn":[0.9382141018],"iteration":53,"passed_time":3.188564794,"remaining_time":14.52568406},
{"learn":[0.9305430695],"iteration":54,"passed_time":3.246752575,"remaining_time":14.46280692},
{"learn":[0.9196235013],"iteration":55,"passed_time":3.319191411,"remaining_time":14.46219115},
{"learn":[0.9124003283],"iteration":56,"passed_time":3.375925452,"remaining_time":14.39210324},
{"learn":[0.905880437],"iteration":57,"passed_time":3.434290139,"remaining_time":14.32927955},
{"learn":[0.9018493203],"iteration":58,"passed_time":3.501172344,"remaining_time":14.3013989},
{"learn":[0.8919189647],"iteration":59,"passed_time":3.556875495,"remaining_time":14.22750198},
{"learn":[0.8866233293],"iteration":60,"passed_time":3.624456559,"remaining_time":14.20073963},
{"learn":[0.8799898628],"iteration":61,"passed_time":3.699546093,"remaining_time":14.20148339},
{"learn":[0.8744649762],"iteration":62,"passed_time":3.757061671,"remaining_time":14.13370819},
{"learn":[0.8679978078],"iteration":63,"passed_time":3.81998823,"remaining_time":14.0862066},
{"learn":[0.8576863452],"iteration":64,"passed_time":3.871198631,"remaining_time":13.99587197},
{"learn":[0.8497781532],"iteration":65,"passed_time":3.930082055,"remaining_time":13.93392729},
{"learn":[0.8446340961],"iteration":66,"passed_time":4.004063799,"remaining_time":13.92458008},
{"learn":[0.8388916304],"iteration":67,"passed_time":4.055668175,"remaining_time":13.83698554},
{"learn":[0.832004822],"iteration":68,"passed_time":4.114465727,"remaining_time":13.7745157},
{"learn":[0.8271910584],"iteration":69,"passed_time":4.177442269,"remaining_time":13.72588174},
{"learn":[0.8215798424],"iteration":70,"passed_time":4.234828441,"remaining_time":13.65881286},
{"learn":[0.8172369215],"iteration":71,"passed_time":4.289522173,"remaining_time":13.58348688},
{"learn":[0.810369341],"iteration":72,"passed_time":4.351449533,"remaining_time":13.53121978},
{"learn":[0.806785482],"iteration":73,"passed_time":4.410373692,"remaining_time":13.46951966},
{"learn":[0.8010953992],"iteration":74,"passed_time":4.470328265,"remaining_time":13.4109848},
{"learn":[0.7955506619],"iteration":75,"passed_time":4.52610298,"remaining_time":13.34009299},
{"learn":[0.7914518056],"iteration":76,"passed_time":4.578465051,"remaining_time":13.25971047},
{"learn":[0.7872083438],"iteration":77,"passed_time":4.639120389,"remaining_time":13.20365034},
{"learn":[0.7835303454],"iteration":78,"passed_time":4.703899196,"remaining_time":13.15900914},
{"learn":[0.7750379011],"iteration":79,"passed_time":4.761843988,"remaining_time":13.09507097},
{"learn":[0.7654187166],"iteration":80,"passed_time":4.824448581,"remaining_time":13.0438795},
{"learn":[0.7598567409],"iteration":81,"passed_time":4.876500272,"remaining_time":12.96435438},
{"learn":[0.7533658435],"iteration":82,"passed_time":4.934834099,"remaining_time":12.90191566},
{"learn":[0.7470256263],"iteration":83,"passed_time":5.057041138,"remaining_time":13.00382007},
{"learn":[0.7412770327],"iteration":84,"passed_time":5.12769319,"remaining_time":12.97004748},
{"learn":[0.734261848],"iteration":85,"passed_time":5.18750464,"remaining_time":12.90844178},
{"learn":[0.7299129917],"iteration":86,"passed_time":5.246811997,"remaining_time":12.84564317},
{"learn":[0.7241985197],"iteration":87,"passed_time":5.300328977,"remaining_time":12.76897435},
{"learn":[0.7128510413],"iteration":88,"passed_time":5.349832605,"remaining_time":12.68331101},
{"learn":[0.7072339614],"iteration":89,"passed_time":5.404257624,"remaining_time":12.60993446},
{"learn":[0.7006073077],"iteration":90,"passed_time":5.451062442,"remaining_time":12.51947308},
{"learn":[0.6898299511],"iteration":91,"passed_time":5.503345917,"remaining_time":12.44234729},
{"learn":[0.6762300908],"iteration":92,"passed_time":5.560034895,"remaining_time":12.37556154},
{"learn":[0.6687713513],"iteration":93,"passed_time":5.620208378,"remaining_time":12.31662687},
{"learn":[0.6583044013],"iteration":94,"passed_time":5.673600075,"remaining_time":12.24303174},
{"learn":[0.6535349469],"iteration":95,"passed_time":5.729352912,"remaining_time":12.17487494},
{"learn":[0.6476494995],"iteration":96,"passed_time":5.779497076,"remaining_time":12.09523615},
{"learn":[0.6418570006],"iteration":97,"passed_time":5.832340174,"remaining_time":12.0217624},
{"learn":[0.6337966438],"iteration":98,"passed_time":5.888777221,"remaining_time":11.95600224},
{"learn":[0.6278578764],"iteration":99,"passed_time":5.940341345,"remaining_time":11.88068269},
{"learn":[0.6181334179],"iteration":100,"passed_time":5.995502983,"remaining_time":11.81292172},
{"learn":[0.6099289287],"iteration":101,"passed_time":6.050065609,"remaining_time":11.74424501},
{"learn":[0.6016325351],"iteration":102,"passed_time":6.100649061,"remaining_time":11.6682317},
{"learn":[0.5942230794],"iteration":103,"passed_time":6.151457973,"remaining_time":11.59313233},
{"learn":[0.5876724713],"iteration":104,"passed_time":6.209707629,"remaining_time":11.53231417},
{"learn":[0.576943729],"iteration":105,"passed_time":6.259976689,"remaining_time":11.45693847},
{"learn":[0.5705257073],"iteration":106,"passed_time":6.309545465,"remaining_time":11.38076892},
{"learn":[0.565817931],"iteration":107,"passed_time":6.360926519,"remaining_time":11.30831381},
{"learn":[0.5538447599],"iteration":108,"passed_time":6.409593576,"remaining_time":11.23148966},
{"learn":[0.5464479691],"iteration":109,"passed_time":6.458273342,"remaining_time":11.15519941},
{"learn":[0.5406379632],"iteration":110,"passed_time":6.513917617,"remaining_time":11.09126513},
{"learn":[0.5334552049],"iteration":111,"passed_time":6.565467813,"remaining_time":11.02060669},
{"learn":[0.528960074],"iteration":112,"passed_time":6.619023753,"remaining_time":10.95360568},
{"learn":[0.5230343161],"iteration":113,"passed_time":6.679538761,"remaining_time":10.89819482},
{"learn":[0.5188429098],"iteration":114,"passed_time":6.734995749,"remaining_time":10.83455838},
{"learn":[0.5103011143],"iteration":115,"passed_time":6.796980585,"remaining_time":10.78141748},
{"learn":[0.5048560177],"iteration":116,"passed_time":6.859618029,"remaining_time":10.72914615},
{"learn":[0.4988145122],"iteration":117,"passed_time":6.916132273,"remaining_time":10.66725486},
{"learn":[0.4941872758],"iteration":118,"passed_time":6.97234704,"remaining_time":10.60499844},
{"learn":[0.4902984374],"iteration":119,"passed_time":7.02931781,"remaining_time":10.54397672},
{"learn":[0.4868561341],"iteration":120,"passed_time":7.083603518,"remaining_time":10.47904983},
{"learn":[0.4825011221],"iteration":121,"passed_time":7.137837418,"remaining_time":10.41422181},
{"learn":[0.4750489653],"iteration":122,"passed_time":7.193963564,"remaining_time":10.35228903},
{"learn":[0.4711389187],"iteration":123,"passed_time":7.248266489,"remaining_time":10.28786211},
{"learn":[0.4670148327],"iteration":124,"passed_time":7.306651739,"remaining_time":10.22931243},
{"learn":[0.4595916811],"iteration":125,"passed_time":7.359163989,"remaining_time":10.16265503},
{"learn":[0.4533451155],"iteration":126,"passed_time":7.417104192,"remaining_time":10.10361437},
{"learn":[0.4457616952],"iteration":127,"passed_time":7.482437316,"remaining_time":10.05452514},
{"learn":[0.4406960979],"iteration":128,"passed_time":7.547166432,"remaining_time":10.00438341},
{"learn":[0.4352479346],"iteration":129,"passed_time":7.611294217,"remaining_time":9.953230899},
{"learn":[0.4295620315],"iteration":130,"passed_time":7.666467085,"remaining_time":9.890327766},
{"learn":[0.4209192596],"iteration":131,"passed_time":7.731095944,"remaining_time":9.839576655},
{"learn":[0.4164236291],"iteration":132,"passed_time":7.787544195,"remaining_time":9.778344967},
{"learn":[0.4108598618],"iteration":133,"passed_time":7.853100211,"remaining_time":9.728467426},
{"learn":[0.4034226003],"iteration":134,"passed_time":7.914179426,"remaining_time":9.672885965},
{"learn":[0.3978173441],"iteration":135,"passed_time":7.972479891,"remaining_time":9.613872809},
{"learn":[0.3940133739],"iteration":136,"passed_time":8.034187655,"remaining_time":9.558923998},
{"learn":[0.3893094047],"iteration":137,"passed_time":8.092280821,"remaining_time":9.499634007},
{"learn":[0.3847059851],"iteration":138,"passed_time":8.147691055,"remaining_time":9.437253669},
{"learn":[0.3813194189],"iteration":139,"passed_time":8.208042493,"remaining_time":9.380619992},
{"learn":[0.3776636147],"iteration":140,"passed_time":8.260752824,"remaining_time":9.315317015},
{"learn":[0.3730734429],"iteration":141,"passed_time":8.312262165,"remaining_time":9.248855085},
{"learn":[0.3705772902],"iteration":142,"passed_time":8.368419321,"remaining_time":9.187705129},
{"learn":[0.3674478656],"iteration":143,"passed_time":8.419502884,"remaining_time":9.121128124},
{"learn":[0.3610191853],"iteration":144,"passed_time":8.473672752,"remaining_time":9.058063977},
{"learn":[0.3576817594],"iteration":145,"passed_time":8.537748227,"remaining_time":9.005570048},
{"learn":[0.3542266679],"iteration":146,"passed_time":8.591003146,"remaining_time":8.941656335},
{"learn":[0.3475412914],"iteration":147,"passed_time":8.651715949,"remaining_time":8.88554611},
{"learn":[0.343677969],"iteration":148,"passed_time":8.730093496,"remaining_time":8.847275959},
{"learn":[0.3390100139],"iteration":149,"passed_time":8.784976306,"remaining_time":8.784976306},
{"learn":[0.3356202931],"iteration":150,"passed_time":8.845208569,"remaining_time":8.728053489},
{"learn":[0.3315733941],"iteration":151,"passed_time":8.91241289,"remaining_time":8.677875708},
{"learn":[0.3277854087],"iteration":152,"passed_time":8.975120282,"remaining_time":8.623154781},
{"learn":[0.3241595111],"iteration":153,"passed_time":9.032420607,"remaining_time":8.563203952},
{"learn":[0.3184651444],"iteration":154,"passed_time":9.104424788,"remaining_time":8.517042544},
{"learn":[0.3153719013],"iteration":155,"passed_time":9.178046199,"remaining_time":8.472042645},
{"learn":[0.3106552781],"iteration":156,"passed_time":9.290185203,"remaining_time":8.461761045},
{"learn":[0.3065956445],"iteration":157,"passed_time":9.3678701,"remaining_time":8.419225027},
{"learn":[0.3033923895],"iteration":158,"passed_time":9.460591015,"remaining_time":8.389580712},
{"learn":[0.3003856918],"iteration":159,"passed_time":9.542064823,"remaining_time":8.34930672},
{"learn":[0.2966314709],"iteration":160,"passed_time":9.604121445,"remaining_time":8.291757024},
{"learn":[0.2940147775],"iteration":161,"passed_time":9.66778409,"remaining_time":8.235519781},
{"learn":[0.2910128095],"iteration":162,"passed_time":9.72394222,"remaining_time":8.172883952},
{"learn":[0.2862216818],"iteration":163,"passed_time":9.797093762,"remaining_time":8.124419218},
{"learn":[0.28352918],"iteration":164,"passed_time":9.863127576,"remaining_time":8.069831653},
{"learn":[0.28038077],"iteration":165,"passed_time":9.917946757,"remaining_time":8.006053406},
{"learn":[0.2758417282],"iteration":166,"passed_time":9.989348504,"remaining_time":7.955588928},
{"learn":[0.2728135679],"iteration":167,"passed_time":10.04404184,"remaining_time":7.891747163},
{"learn":[0.2688988454],"iteration":168,"passed_time":10.10290192,"remaining_time":7.831243498},
{"learn":[0.2658258489],"iteration":169,"passed_time":10.16634825,"remaining_time":7.774266306},
{"learn":[0.2626614129],"iteration":170,"passed_time":10.2272003,"remaining_time":7.715256364},
{"learn":[0.2596739044],"iteration":171,"passed_time":10.28702763,"remaining_time":7.655462422},
{"learn":[0.2561446974],"iteration":172,"passed_time":10.34005218,"remaining_time":7.590674146},
{"learn":[0.2518596935],"iteration":173,"passed_time":10.39245642,"remaining_time":7.525571892},
{"learn":[0.2478056771],"iteration":174,"passed_time":10.44889087,"remaining_time":7.463493476},
{"learn":[0.2455972708],"iteration":175,"passed_time":10.50829421,"remaining_time":7.403570923},
{"learn":[0.2421054912],"iteration":176,"passed_time":10.56554246,"remaining_time":7.342156623},
{"learn":[0.2399036608],"iteration":177,"passed_time":10.63031514,"remaining_time":7.28594633},
{"learn":[0.2367251339],"iteration":178,"passed_time":10.70148362,"remaining_time":7.233963788},
{"learn":[0.2331059954],"iteration":179,"passed_time":10.76135394,"remaining_time":7.174235963},
{"learn":[0.2302258089],"iteration":180,"passed_time":10.82565735,"remaining_time":7.117421132},
{"learn":[0.2280712847],"iteration":181,"passed_time":10.89119156,"remaining_time":7.061321998},
{"learn":[0.2262583356],"iteration":182,"passed_time":10.94968681,"remaining_time":7.000619438},
{"learn":[0.2242570653],"iteration":183,"passed_time":11.00722169,"remaining_time":6.939335414},
{"learn":[0.2226058798],"iteration":184,"passed_time":11.0786513,"remaining_time":6.886729188},
{"learn":[0.2210096447],"iteration":185,"passed_time":11.13884749,"remaining_time":6.827035556},
{"learn":[0.2189149006],"iteration":186,"passed_time":11.19689116,"remaining_time":6.766035834},
{"learn":[0.2171530521],"iteration":187,"passed_time":11.2527429,"remaining_time":6.703761725},
{"learn":[0.2154324301],"iteration":188,"passed_time":11.30830396,"remaining_time":6.641384863},
{"learn":[0.2140913048],"iteration":189,"passed_time":11.36254967,"remaining_time":6.578318232},
{"learn":[0.2121071986],"iteration":190,"passed_time":11.41572127,"remaining_time":6.514730984},
{"learn":[0.2099684224],"iteration":191,"passed_time":11.47450969,"remaining_time":6.4544117},
{"learn":[0.2080014116],"iteration":192,"passed_time":11.53164416,"remaining_time":6.393191323},
{"learn":[0.2064661074],"iteration":193,"passed_time":11.58661846,"remaining_time":6.330832768},
{"learn":[0.2043037695],"iteration":194,"passed_time":11.64591518,"remaining_time":6.270877402},
{"learn":[0.2016884284],"iteration":195,"passed_time":11.7108276,"remaining_time":6.213908521},
{"learn":[0.198640882],"iteration":196,"passed_time":11.76925876,"remaining_time":6.153470315},
{"learn":[0.1967499241],"iteration":197,"passed_time":11.83478275,"remaining_time":6.096706263},
{"learn":[0.1944642423],"iteration":198,"passed_time":11.89570388,"remaining_time":6.037518048},
{"learn":[0.1929557406],"iteration":199,"passed_time":11.95399543,"remaining_time":5.976997715},
{"learn":[0.1907502705],"iteration":200,"passed_time":12.01620925,"remaining_time":5.91843142},
{"learn":[0.1887630183],"iteration":201,"passed_time":12.07209491,"remaining_time":5.856758915},
{"learn":[0.1870013567],"iteration":202,"passed_time":12.13057341,"remaining_time":5.79638237},
{"learn":[0.1852750018],"iteration":203,"passed_time":12.19256719,"remaining_time":5.737678676},
{"learn":[0.1839963096],"iteration":204,"passed_time":12.24665442,"remaining_time":5.675278878},
{"learn":[0.1826381349],"iteration":205,"passed_time":12.3008783,"remaining_time":5.613022135},
{"learn":[0.1806123719],"iteration":206,"passed_time":12.35365882,"remaining_time":5.550194543},
{"learn":[0.1791362739],"iteration":207,"passed_time":12.40476941,"remaining_time":5.486724932},
{"learn":[0.1778915053],"iteration":208,"passed_time":12.47147568,"remaining_time":5.430164052},
{"learn":[0.1765453824],"iteration":209,"passed_time":12.52428862,"remaining_time":5.367552266},
{"learn":[0.1753309099],"iteration":210,"passed_time":12.57931573,"remaining_time":5.305967299},
{"learn":[0.1740790589],"iteration":211,"passed_time":12.63840581,"remaining_time":5.246130713},
{"learn":[0.172347197],"iteration":212,"passed_time":12.69241091,"remaining_time":5.184224176},
{"learn":[0.1712082609],"iteration":213,"passed_time":12.7463022,"remaining_time":5.122345744},
{"learn":[0.1701985445],"iteration":214,"passed_time":12.80774401,"remaining_time":5.063526703},
{"learn":[0.1682333977],"iteration":215,"passed_time":12.85880118,"remaining_time":5.000644901},
{"learn":[0.1670810488],"iteration":216,"passed_time":12.91384201,"remaining_time":4.939395792},
{"learn":[0.165208403],"iteration":217,"passed_time":12.9873413,"remaining_time":4.885146728},
{"learn":[0.1631498183],"iteration":218,"passed_time":13.03640332,"remaining_time":4.821683421},
{"learn":[0.1619166486],"iteration":219,"passed_time":13.09234256,"remaining_time":4.760851839},
{"learn":[0.1608367937],"iteration":220,"passed_time":13.14913077,"remaining_time":4.700368014},
{"learn":[0.1593428476],"iteration":221,"passed_time":13.20239378,"remaining_time":4.638678896},
{"learn":[0.1581681395],"iteration":222,"passed_time":13.25452646,"remaining_time":4.576675056},
{"learn":[0.1572618524],"iteration":223,"passed_time":13.33533631,"remaining_time":4.524489104},
{"learn":[0.1564552484],"iteration":224,"passed_time":13.40183724,"remaining_time":4.467279081},
{"learn":[0.1549761169],"iteration":225,"passed_time":13.4575724,"remaining_time":4.40646176},
{"learn":[0.1538082803],"iteration":226,"passed_time":13.51466854,"remaining_time":4.346126886},
{"learn":[0.1522705088],"iteration":227,"passed_time":13.57244794,"remaining_time":4.286036193},
{"learn":[0.1511145205],"iteration":228,"passed_time":13.62868978,"remaining_time":4.225488972},
{"learn":[0.1490054701],"iteration":229,"passed_time":13.69275264,"remaining_time":4.167359499},
{"learn":[0.1480810177],"iteration":230,"passed_time":13.75803676,"remaining_time":4.109543449},
{"learn":[0.1470014719],"iteration":231,"passed_time":13.81402839,"remaining_time":4.048939355},
{"learn":[0.145712992],"iteration":232,"passed_time":13.87901988,"remaining_time":3.990962797},
{"learn":[0.1446024215],"iteration":233,"passed_time":13.93883823,"remaining_time":3.931467192},
{"learn":[0.1435843804],"iteration":234,"passed_time":13.99574068,"remaining_time":3.871162317},
{"learn":[0.14192117],"iteration":235,"passed_time":14.05153102,"remaining_time":3.810584684},
{"learn":[0.1400062077],"iteration":236,"passed_time":14.11296694,"remaining_time":3.751548175},
{"learn":[0.1383149575],"iteration":237,"passed_time":14.17939721,"remaining_time":3.693792552},
{"learn":[0.1370356339],"iteration":238,"passed_time":14.24872024,"remaining_time":3.636702657},
{"learn":[0.1358983237],"iteration":239,"passed_time":14.30775213,"remaining_time":3.576938033},
{"learn":[0.134486283],"iteration":240,"passed_time":14.36486002,"remaining_time":3.516708469},
{"learn":[0.133258493],"iteration":241,"passed_time":14.42503551,"remaining_time":3.457239916},
{"learn":[0.1324804877],"iteration":242,"passed_time":14.48010232,"remaining_time":3.396567211},
{"learn":[0.1313131105],"iteration":243,"passed_time":14.53422065,"remaining_time":3.335722773},
{"learn":[0.1302467766],"iteration":244,"passed_time":14.59217262,"remaining_time":3.275793854},
{"learn":[0.1293706777],"iteration":245,"passed_time":14.65129865,"remaining_time":3.216138728},
{"learn":[0.1285675655],"iteration":246,"passed_time":14.70885163,"remaining_time":3.15615035},
{"learn":[0.127124563],"iteration":247,"passed_time":14.7665391,"remaining_time":3.09620981},
{"learn":[0.126172571],"iteration":248,"passed_time":14.82230169,"remaining_time":3.035893118},
{"learn":[0.1252420376],"iteration":249,"passed_time":14.89802098,"remaining_time":2.979604196},
{"learn":[0.1242626524],"iteration":250,"passed_time":14.95472932,"remaining_time":2.91944915},
{"learn":[0.1234393311],"iteration":251,"passed_time":15.01508097,"remaining_time":2.860015424},
{"learn":[0.1229305181],"iteration":252,"passed_time":15.08558733,"remaining_time":2.802460887},
{"learn":[0.121859897],"iteration":253,"passed_time":15.13708865,"remaining_time":2.741362512},
{"learn":[0.1211543581],"iteration":254,"passed_time":15.19857136,"remaining_time":2.682100829},
{"learn":[0.1204398299],"iteration":255,"passed_time":15.26333989,"remaining_time":2.623386543},
{"learn":[0.119643208],"iteration":256,"passed_time":15.31207354,"remaining_time":2.561942265},
{"learn":[0.1186706464],"iteration":257,"passed_time":15.3643031,"remaining_time":2.501165622},
{"learn":[0.1180080364],"iteration":258,"passed_time":15.42347919,"remaining_time":2.441554622},
{"learn":[0.1172086415],"iteration":259,"passed_time":15.47908917,"remaining_time":2.381398333},
{"learn":[0.1165636177],"iteration":260,"passed_time":15.53549103,"remaining_time":2.321395211},
{"learn":[0.1158788675],"iteration":261,"passed_time":15.58973469,"remaining_time":2.261106558},
{"learn":[0.1151256945],"iteration":262,"passed_time":15.64288478,"remaining_time":2.200710026},
{"learn":[0.114465349],"iteration":263,"passed_time":15.70078581,"remaining_time":2.141016246},
{"learn":[0.1134197162],"iteration":264,"passed_time":15.75520711,"remaining_time":2.080876411},
{"learn":[0.1124850781],"iteration":265,"passed_time":15.80906841,"remaining_time":2.020707992},
{"learn":[0.1120736919],"iteration":266,"passed_time":15.87022026,"remaining_time":1.961487897},
{"learn":[0.111090244],"iteration":267,"passed_time":15.92487421,"remaining_time":1.901477518},
{"learn":[0.1105847014],"iteration":268,"passed_time":15.98541925,"remaining_time":1.842185862},
{"learn":[0.1098158854],"iteration":269,"passed_time":16.04190525,"remaining_time":1.782433917},
{"learn":[0.1093392435],"iteration":270,"passed_time":16.09473581,"remaining_time":1.722314902},
{"learn":[0.1088325812],"iteration":271,"passed_time":16.16111907,"remaining_time":1.663644611},
{"learn":[0.1080582455],"iteration":272,"passed_time":16.22418311,"remaining_time":1.604589539},
{"learn":[0.1069666778],"iteration":273,"passed_time":16.28032512,"remaining_time":1.544848369},
{"learn":[0.1062084642],"iteration":274,"passed_time":16.33291484,"remaining_time":1.48481044},
{"learn":[0.1052459862],"iteration":275,"passed_time":16.38826815,"remaining_time":1.425066796},
{"learn":[0.1047987274],"iteration":276,"passed_time":16.44445493,"remaining_time":1.365424056},
{"learn":[0.1040773536],"iteration":277,"passed_time":16.50135375,"remaining_time":1.305862527},
{"learn":[0.1034945782],"iteration":278,"passed_time":16.56454721,"remaining_time":1.246793876},
{"learn":[0.1027735418],"iteration":279,"passed_time":16.62996655,"remaining_time":1.187854754},
{"learn":[0.1021872595],"iteration":280,"passed_time":16.68879087,"remaining_time":1.128423582},
{"learn":[0.1017551057],"iteration":281,"passed_time":16.74913603,"remaining_time":1.069093789},
{"learn":[0.1010747751],"iteration":282,"passed_time":16.84512555,"remaining_time":1.011898001},
{"learn":[0.1002184882],"iteration":283,"passed_time":16.91691158,"remaining_time":0.9530654414},
{"learn":[0.09967991739],"iteration":284,"passed_time":16.98471052,"remaining_time":0.8939321327},
{"learn":[0.09924016993],"iteration":285,"passed_time":17.03688729,"remaining_time":0.8339735037},
{"learn":[0.0988222378],"iteration":286,"passed_time":17.09225593,"remaining_time":0.7742136833},
{"learn":[0.09814215695],"iteration":287,"passed_time":17.14798429,"remaining_time":0.7144993454},
{"learn":[0.09732520655],"iteration":288,"passed_time":17.19937967,"remaining_time":0.6546476692},
{"learn":[0.09656172806],"iteration":289,"passed_time":17.2489159,"remaining_time":0.5947902034},
{"learn":[0.09615418401],"iteration":290,"passed_time":17.30498651,"remaining_time":0.5352057682},
{"learn":[0.09579011685],"iteration":291,"passed_time":17.35551219,"remaining_time":0.4754934847},
{"learn":[0.09511814503],"iteration":292,"passed_time":17.40623809,"remaining_time":0.4158486915},
{"learn":[0.09465963353],"iteration":293,"passed_time":17.46180849,"remaining_time":0.3563634386},
{"learn":[0.09378444494],"iteration":294,"passed_time":17.5348539,"remaining_time":0.2972009135},
{"learn":[0.09343161378],"iteration":295,"passed_time":17.5971002,"remaining_time":0.2377986513},
{"learn":[0.09289425668],"iteration":296,"passed_time":17.66760954,"remaining_time":0.1784607025},
{"learn":[0.09245023352],"iteration":297,"passed_time":17.7205867,"remaining_time":0.1189301121},
{"learn":[0.09204597576],"iteration":298,"passed_time":17.79016642,"remaining_time":0.05949888436},
{"learn":[0.09159022591],"iteration":299,"passed_time":17.85811409,"remaining_time":0}
]}